gama_pettingzoo/__init__.py
gama_pettingzoo/gama_AEC_env.py
gama_pettingzoo/gama_client_wrapper.py
gama_pettingzoo/gama_parallel_env.py
gama_pettingzoo-0.1.0.dist-info/METADATA
gama_pettingzoo-0.1.0.dist-info/WHEEL
gama_pettingzoo-0.1.0.dist-info/licenses/LICENSE
gama_pettingzoo-0.1.0.dist-info/RECORD
